{
  "id": "deep-learning-intro",
  "title": "Deep Learning pour l'impatient",
  "description": "Comprendre les réseaux de neurones de zéro à expert : neurones, propagation, rétropropagation et optimisation Adam, avec un laboratoire interactif pour expérimenter en temps réel.",
  "hierarchy": ["ia"],
  "tags": ["ia", "deep-learning", "neural-network", "machine-learning", "interactif"],
  "metadata": {
    "author": "cyrille",
    "created": "2025-12-15",
    "duration": "30 min",
    "difficulty": "beginner",
    "language": "fr"
  },
  "icon": "🧠",
  "content": [
    { "id": "01-retropropagation" }
  ]
}
